vaccinegov/__init__.py
vaccinegov/main.py
vaccinegov/schemas/__init__.py
vaccinegov/schemas/manufacturers.py
vaccinegov/schemas/providers.py
vaccinegov-0.0.1.dist-info/WHEEL
vaccinegov-0.0.1.dist-info/METADATA
vaccinegov-0.0.1.dist-info/RECORD
