Metadata-Version: 2.1
Name: vaccinegov
Version: 0.0.1
Summary: A library to interact with the U.S Government's COVID-19 Vaccine Finder tool
License: MIT
Author: Mustafa
Author-email: mustafa@ms7m.me
Requires-Python: >=3.7,<4.0
Classifier: License :: OSI Approved :: MIT License
Classifier: Programming Language :: Python :: 3
Classifier: Programming Language :: Python :: 3.7
Classifier: Programming Language :: Python :: 3.8
Classifier: Programming Language :: Python :: 3.9
Requires-Dist: arrow (>=1.1.0,<2.0.0)
Requires-Dist: httpx (>=0.18.1,<0.19.0)
Requires-Dist: loguru (>=0.5.3,<0.6.0)
